stcache/__init__.py
stcache/client.py
stcache/stcache.py
stcache-0.0.3.dist-info/METADATA
stcache-0.0.3.dist-info/WHEEL
stcache-0.0.3.dist-info/top_level.txt
stcache-0.0.3.dist-info/RECORD
